filesortify/__init__.py
filesortify/organizer.py
FileSortify-0.1.1.dist-info/LICENSE
FileSortify-0.1.1.dist-info/METADATA
FileSortify-0.1.1.dist-info/WHEEL
FileSortify-0.1.1.dist-info/top_level.txt
FileSortify-0.1.1.dist-info/RECORD
