Metadata-Version: 2.1
Name: FileSortify
Version: 0.1.1
Summary: A tool for organizing files by extension.
Home-page: https://github.com/himanshu-kr-jha/
Author: Himanshu Kumar Jha
Author-email: himanshukrjha004@gmail.com
Classifier: Programming Language :: Python :: 3
Classifier: License :: OSI Approved :: MIT License
Classifier: Operating System :: OS Independent
Requires-Python: >=3.6
License-File: LICENSE
